modulos_proyecto1.v
//Modulo para FlipFlop de cinco bits
module FlipFlopD5(
    input wire reset, clk,
    input wire [4:0] D,
    output reg [4:0] S);
        always @ (posedge clk, posedge reset) begin
            if (reset) begin
                S <= 5'b0;
            end
            else
                S <= D;
        end
endmodule

//Modulo para FlipFlop de dos bits      
module FlipFlopD2(
    input wire reset, clk,
    input wire [1:0] D,
    output reg [1:0] S);
        always @ (posedge clk, posedge reset) begin
            if (reset) begin
                S <= 2'b0;
            end
            else
                S <= D;
        end
endmodule

//Modulo para FlipFlop de un bits      
module FlipFlopD1(
    input wire reset, clk,
    input wire D,
    output reg S);
        always @ (posedge clk, posedge reset) begin
            if (reset) begin
                S <= 1'b0;
            end
            else
                S <= D;
        end
endmodule

//Modulo para Anti Rebote 1
module antirebote1(
    input wire clk, reset, PB1,   
    output wire out);
    wire Y1, Y2;
    assign Y1 = PB1;
    FlipFlopD1 E1(clk, reset, Y1, Y2);
    assign  Out = (~Y2 & PB1);
endmodule

//Modulo para Anti Rebote 2
module antirebote2(
    input wire clk, reset, PB2,   
    output wire out);
    wire Y1, Y2;
    assign Y1 = PB2;
    FlipFlopD1 E1(clk, reset, Y1, Y2);
    assign  Out = (~Y2 & PB2);
endmodule

//Modulo para Anti Rebote 3
module antirebote3(
    input wire clk, reset, PB3,   
    output wire out);
    wire Y1, Y2;
    assign Y1 = PB3;
    FlipFlopD1 E1(clk, reset, Y1, Y2);
    assign  Out = (~Y2 & PB3);
endmodule



//Modulo de memoria para la variable tipo 
module Memoria1(
    input wire clk, reset, Y,
    input wire [1:0] T,
    output wire T2);
    wire [1:0] E; //Estados actuales
    wire [1:0] EF; //Estados futuros
    
    //Ecuaciones para los estados Futuros
    assign EF[1] = (~E[1] & ~E[0] & T[1] & ~T[0] & ~Y) | (E[1] & ~E[0] & ~T[1] & ~T[0] & ~ Y);
    assign EF[0] = (~E[1] & ~E[0] & ~T[1] & T[0] & ~Y) | (~E[1] & E[0] & ~T[1] & ~T[0] & ~Y);

    //Implementación de FlipFlop tipo D de 2 bits
    FlipFlopD2 R1(clk, reset, EF, E);

    //Ecuaciones para las salidas
    assign T2 = ~E[0];

endmodule

//Modulo de memoria para variable Tamaño
module Memoria2(
    input wire clk, reset, Y,
    input wire [1:0] Ta, 
    output wire [1:0] Ta2);
    wire [1:0] E; //Estados actuales
    wire [1:0] EF; //Estados Futuros

    //Ecuaciones para los estados Futuros
    assign EF[1] = (~E[1] & ~E[0] & Ta[1] & ~Y) | (E[1] & ~Ta[1] & ~Ta[0] & ~Y);
    assign EF[0] = (~E[1] & ~E[0] & Ta[0] & ~Y) | (E[0] & ~Ta[1] & ~Ta[0] & ~Y);

    //Ecuaciones para las salidas
    assign Ta2[1] = (E[1] & E[0]);
    assign Ta2[0] = ~E[0];



    //Implementación de FlipFlop tipo D de 2 bits
    FlipFlopD2 R2(clk, reset, EF, E);

endmodule

//Modulo de memoria para variable Principal
module Memoria3(
    input wire clk, reset, Y, 
    input wire [1:0] P, 
    output wire [1:0] P2);
    wire [1:0] E; //Estados actuales
    wire [1:0] EF; //Estados Futuros

    //Ecuaciones para los estados Futuros
    assign EF[1] = (~E[1] & ~E[0] & P[1] & ~Y) | (E[1] & ~P[1] & ~P[0] & ~Y);
    assign EF[0] = (~E[1] & ~E[0] & P[0] & ~Y) | (E[0] & ~P[1] & ~P[0] & ~Y);
    
    //Ecuaciones para las salidas
    assign P2[1] = (E[1] & E[0]);
    assign P2[0] = ~E[0];

    //Implementación de FlipFlop tipo D de 2 bits
    FlipFlopD2 R3(clk, reset, EF, E);


endmodule


//Modulo de memoria para la variable Acomp 
module Memoria4(
    input wire clk, reset, Y,
    input wire [1:0] Ac,
    output wire Ac2);
    wire [1:0] E; //Estados actuales
    wire [1:0] EF; //Estados futuros
    
    //Ecuaciones para los estados Futuros
    assign EF[1] = (~E[1] & ~E[0] & Ac[1] & ~Ac[0] & ~Y) | (E[1] & ~E[0] & ~Ac[1] & ~Ac[0] & ~Y);
    assign EF[0] = (~E[1] & ~E[0] & ~Ac[1] & Ac[0] & ~Y) | (~E[1] & E[0] & ~Ac[1] & ~Ac[0] & ~Y);

    //Implementación de FlipFlop tipo D de 2 bits
    FlipFlopD2 R4(clk, reset, EF, E);

    //Ecuaciones para las salidas
    assign Ac2 = ~E[0];

endmodule

//Modulo de memoria para variable Bebida
module Memoria5(
    input wire clk, reset, Y,
    input wire [1:0] B,
    output wire B2);
    wire [1:0] E; //Estados actuales
    wire [1:0] EF; //Estados futuros
    
    //Ecuaciones para los estados Futuros
    assign EF[1] = (~E[1] & ~E[0] & B[1] & ~B[0] & ~Y) | (E[1] & ~E[0] & ~B[1] & ~B[0] & ~Y);
    assign EF[0] = (~E[1] & ~E[0] & ~B[1] & B[0] & ~Y) | (~E[1] & E[0] & ~B[1] & ~B[0] & ~Y);

    //Implementación de FlipFlop tipo D de 2 bits
    FlipFlopD2 R5(clk, reset, EF, E);

    //Ecuaciones para las salidas
    assign B2 = ~E[0];

endmodule


//Modulo de la FSM 
module FSM(
    input wire clk, reset, PB1, PB2, PB3, 
    input wire [1:0] A,
    output wire [1:0] T, 
    output wire [1:0] Ta, 
    output wire [1:0] P, 
    output wire [1:0] Ac, 
    output wire [1:0]B, 
    output wire Y);
    wire [4:0]E; //Estados actuales
    wire [4:0]EF; //Estados futuros
    

    assign EF[4] = (E[4] & ~E[3] & ~E[2] & E[1] & ~E[0] & ~PB1 & ~PB3) | (E[4] & ~E[3] & ~E[2] & ~E[1] & ~PB1 & ~PB2 & ~PB3) | (~E[4] & E[3] & E[2] & E[1] & E[0] & ~PB1 & PB2 & ~PB3) | (~E[4] & E[3] & E[2] & E[1] & E[0] & PB1 & ~PB2 & ~PB3);
    assign EF[3] = (~E[4] & E[3] & ~PB1 & ~PB2 & ~PB3) | (~E[4] & E[2] & E[1] & ~PB1 & ~PB2 & ~PB3) | (~E[4] & E[2] & E[0] & ~PB1 & ~PB2 & ~PB3) | (~E[4] & E[3] & E[2] & ~E[1] & ~E[0] & ~PB1 & ~PB3) | (~E[4] & E[3] & E[2] & ~E[1] & ~E[0] & ~PB2 & ~PB3);
    assign EF[2] = (~E[4] & ~E[2] & E[1] & ~PB1 & ~PB2 & ~PB3) | (~E[4] & E[3] & E[0] & ~PB1 & ~PB2 & ~PB3) | (~E[4] & E[3] & E[2] & ~E[1] & ~E[0] & ~PB1 & ~PB3) | (~E[4] & E[3] & E[2] & ~E[1] & ~E[0] & ~PB2 & ~PB3) | (~E[4] & E[2] & ~E[1] & ~E[0] & ~PB1 & ~PB2 & ~PB3) | (~E[4] & E[3] & E[1] & ~PB1 & ~PB2 & ~PB3);
    assign EF[1] = (E[4] & ~E[3] & ~E[2] & E[1] & ~E[0] & ~PB1 & ~PB3) | (~E[4] & E[3] & E[2] & E[1] & ~PB1 & ~PB2 & ~PB3) | (E[4] & ~E[3] & ~E[2] & ~E[1] & ~PB1 & ~PB2 & ~PB3) | (~E[4] & E[3] & E[2] & E[0] & ~PB1 & ~PB2 & ~PB3) | (~E[4] & ~E[3] & ~E[2] & ~E[1] & E[0] & ~PB1 & PB2 & ~PB3) | (~E[4] & E[3] & E[2] & ~E[1] & ~E[0] & ~PB1 & ~PB2 & ~PB3) | (~E[4] & ~E[3] & ~E[2] & ~E[1] & E[0] & PB1 & ~PB2 & ~PB3) | (~E[4] & ~E[3] & E[2] & ~E[1] & ~E[0] & ~PB1 & ~PB2 & ~PB3 & A[1]) | (~E[4] & E[3] & ~E[2] & ~E[1] & ~E[0] & ~PB1 & ~PB2 & ~PB3 & A[1]);
    assign EF[0] = (~E[4] & E[3] & E[2] & E[1] & E[0] & ~PB1 & ~PB3) | (~E[4] & ~E[3] & ~E[2] & ~E[1] & E[0] & ~PB1 & ~PB3) | (~E[4] & E[3] & E[2] & E[1] & ~PB1 & ~PB2 & ~PB3) | (~E[4] & E[3] & E[2] & E[0] & ~PB1 & ~PB2 & ~PB3) | (E[4] & ~E[3] & ~E[2] & E[1] & ~E[0] & ~PB1 & PB2 & ~PB3) | (~E[4] & E[3] & E[2] & ~E[1] & ~E[0] & PB1 & ~PB2 & ~PB3) | (~E[4] & ~E[3] & ~E[2] & ~E[1] & ~E[0] & PB1 & ~PB2 & ~PB3) | (~E[4] & ~E[3] & E[2] & ~E[1] & ~E[0] & ~PB1 & ~PB2 & ~PB3 & A[0]) | (~E[4] & E[3] & ~E[2] & ~E[1] & ~E[0] & ~PB1 & ~PB2 & ~PB3 & A[0]);

    // Implementación de flip FlopFipo D de cinco bits

    FlipFlopD5 S1(clk, reset, EF, E);
    
    //Ecuaciones para las salidas
    
    assign T[1] = (~E[4] & ~E[3] & ~E[2] & E[1] & ~E[0]);
    assign T[0] = (~E[4] & ~E[3] & ~E[2] & E[1] & E[0]);
    assign Ta[1] = (~E[4] & ~E[3] & E[2] & E[1]);
    assign Ta[0] = (~E[4] & ~E[3] & E[2] & E[0]);
    assign P[1] = (~E[4] & E[3] & ~E[2] & E[1]);
    assign P[0] = (~E[4] & E[3] & ~E[2] & E[0]);
    assign Ac[1] = (~E[4] & E[3] & E[2] & E[1] & ~E[0]);
    assign Ac[0] = (~E[4] & E[3] & E[2] & ~E[1] & E[0]);
    assign B[1] = (E[4] & ~E[3] & ~E[2] & ~E[1] & E[0]);
    assign B[0] = (E[4] & ~E[3] & ~E[2] & ~E[1] & ~E[0]);
    assign Y = (E[4] & ~E[3] & ~E[2] & E[1] & ~E[0]);

endmodule

module main(
    input wire clk, reset, PB1, PB2, PB3, 
    input wire [1:0] A,
    output wire T2, Ac2, B2,
    output wire [1:0] Ta2,
    output wire [1:0] P2);
    wire K1, K2, K3, Y;
    wire [1:0] T;
    wire [1:0] Ta;
    wire [1:0] P;
    wire [1:0] Ac;
    wire [1:0] B;
    antirebote1 J1(clk, reset, PB1, K1);
    antirebote2 J2(clk, reset, PB2, K2);
    antirebote3 J3(clk, reset, PB3, K3);
    FSM I(clk, reset, K1, K2, K3, A, T, Ta, P, Ac, B, Y);
    Memoria1 W(clk, reset, Y, T, T2);
    Memoria2 W1(clk, reset, Y, Ta, Ta2);
    Memoria3 W2(clk , reset, Y, P, P2);
    Memoria4 W3(clk, reset, Y, Ac, Ac2);
    Memoria5 W4(clk, reset, Y, B, B2);
endmodule

Proyecto1_tb.v
module testbench();
reg clk, reset, PB1, PB2, PB3;
reg [1:0] A;
wire T2, Ac2, B2;
wire [1:0] Ta2;
wire [1:0] P2;

initial begin 
    clk <= 1;
    forever #5 clk = ~clk;
end

//Se llama a mi main
main M1(clk, reset, PB1, PB2, PB3, A, T2, Ac2, B2, Ta2, P2);

initial begin
    #2
    $display("\n");
    $display("Bienvenido a Diego's");
    $display("clk reset PB1 PB2 PB3 A");
    $monitor("%b  %b  %b  %b  %b  %b", clk, reset, PB1, PB2, PB3, A);

    //Opción de menú 1
    #2 reset = 1;
    #2 reset = 0;
    #4 PB1 = 1; PB2 = 0; PB3 = 0; A = 2'b00;
    #4 PB1 = 1; PB2 = 0; PB3 = 0; A = 2'b00;
    #4 PB1 = 0; PB2 = 0; PB3 = 0; A = 2'b01;
    #4 PB1 = 0; PB2 = 0; PB3 = 0; A = 2'b01;
    #4 PB1 = 1; PB2 = 0; PB3 = 0; A = 2'b00;
    #4 PB1 = 1; PB2 = 0; PB3 = 0; A = 2'b00;
    #4 PB1 = 0; PB2 = 1; PB3 = 0; A = 2'b00;

    //Opción de menú 2
    #2 reset = 1;
    #2 reset = 0;
    #4 PB1 = 1; PB2 = 0; PB3 = 0; A = 2'b00;
    #4 PB1 = 0; PB2 = 1; PB3 = 0; A = 2'b00;
    #4 PB1 = 0; PB2 = 0; PB3 = 0; A = 2'b10;
    #4 PB1 = 0; PB2 = 0; PB3 = 0; A = 2'b10;
    #4 PB1 = 0; PB2 = 1; PB3 = 0; A = 2'b00;
    #4 PB1 = 0; PB2 = 1; PB3 = 0; A = 2'b00;
    #4 PB1 = 0; PB2 = 1; PB3 = 0; A = 2'b00;

    //Opcion de menú 3
    #2 reset = 1;
    #2 reset = 0;
    #4 PB1 = 1; PB2 = 0; PB3 = 0; A = 2'b00;
    #4 PB1 = 0; PB2 = 1; PB3 = 0; A = 2'b00;
    #4 PB1 = 0; PB2 = 0; PB3 = 0; A = 2'b11;
    #4 PB1 = 0; PB2 = 0; PB3 = 0; A = 2'b11;
    #4 PB1 = 0; PB2 = 1; PB3 = 0; A = 2'b00;
    #4 PB1 = 1; PB2 = 0; PB3 = 0; A = 2'b00;
    #4 PB1 = 0; PB2 = 1; PB3 = 0; A = 2'b00;
    
    //Opcion de menú 4
    #2 reset = 1;
    #2 reset = 0;
    #4 PB1 = 1; PB2 = 0; PB3 = 0; A = 2'b00;
    #4 PB1 = 1; PB2 = 0; PB3 = 0; A = 2'b00;
    #4 PB1 = 0; PB2 = 0; PB3 = 0; A = 2'b01;
    #4 PB1 = 0; PB2 = 0; PB3 = 0; A = 2'b10;
    #4 PB1 = 1; PB2 = 0; PB3 = 0; A = 2'b00;
    #4 PB1 = 0; PB2 = 1; PB3 = 0; A = 2'b00;
    #4 PB1 = 0; PB2 = 1; PB3 = 0; A = 2'b00;

    //Opcion de menú 5
    #2 reset = 1;
    #2 reset = 0;
    #4 PB1 = 1; PB2 = 0; PB3 = 0; A = 2'b00;
    #4 PB1 = 1; PB2 = 0; PB3 = 0; A = 2'b00;
    #4 PB1 = 0; PB2 = 0; PB3 = 0; A = 2'b11;
    #4 PB1 = 0; PB2 = 0; PB3 = 0; A = 2'b10;
    #4 PB1 = 0; PB2 = 1; PB3 = 0; A = 2'b00;
    #4 PB1 = 1; PB2 = 0; PB3 = 0; A = 2'b00;
    #4 PB1 = 0; PB2 = 1; PB3 = 0; A = 2'b00;

    //Opcion de menú cancelado en el estado "principal"
    #2 reset = 1;
    #2 reset = 0;
    #4 PB1 = 1; PB2 = 0; PB3 = 0; A = 2'b00;
    #4 PB1 = 0; PB2 = 1; PB3 = 0; A = 2'b00;
    #4 PB1 = 0; PB2 = 0; PB3 = 0; A = 2'b01;
    #4 PB1 = 0; PB2 = 0; PB3 = 1; A = 2'b00;
    #4 PB1 = 0; PB2 = 0; PB3 = 0; A = 2'b00;
    #4 PB1 = 0; PB2 = 0; PB3 = 0; A = 2'b00;
    #4 PB1 = 0; PB2 = 0; PB3 = 0; A = 2'b00;

    //Opcion de menú cancelado en el estado "Acompañamiento"
    #2 reset = 1;
    #2 reset = 0;
    #4 PB1 = 1; PB2 = 0; PB3 = 0; A = 2'b00;
    #4 PB1 = 0; PB2 = 1; PB3 = 0; A = 2'b00;
    #4 PB1 = 0; PB2 = 0; PB3 = 0; A = 2'b01;
    #4 PB1 = 0; PB2 = 0; PB3 = 0; A = 2'b10;
    #4 PB1 = 0; PB2 = 0; PB3 = 1; A = 2'b00;
    #4 PB1 = 0; PB2 = 0; PB3 = 0; A = 2'b00;
    #4 PB1 = 0; PB2 = 0; PB3 = 0; A = 2'b00;

end

initial
    #240 $finish;

initial begin
    $dumpfile ("Proyecto1_tb.vcd");
    $dumpvars(0, testbench);
end 
endmodule

Proyecto1_tb.vcd
$date
	Sat Oct 17 23:58:52 2020
$end
$version
	Icarus Verilog
$end
$timescale
	1ps
$end
$scope module testbench $end
$var wire 2 ! Ta2 [1:0] $end
$var wire 1 " T2 $end
$var wire 2 # P2 [1:0] $end
$var wire 1 $ B2 $end
$var wire 1 % Ac2 $end
$var reg 2 & A [1:0] $end
$var reg 1 ' PB1 $end
$var reg 1 ( PB2 $end
$var reg 1 ) PB3 $end
$var reg 1 * clk $end
$var reg 1 + reset $end
$scope module M1 $end
$var wire 2 , A [1:0] $end
$var wire 1 - K1 $end
$var wire 1 . K2 $end
$var wire 1 / K3 $end
$var wire 1 ' PB1 $end
$var wire 1 ( PB2 $end
$var wire 1 ) PB3 $end
$var wire 1 * clk $end
$var wire 1 + reset $end
$var wire 1 0 Y $end
$var wire 2 1 Ta2 [1:0] $end
$var wire 2 2 Ta [1:0] $end
$var wire 1 " T2 $end
$var wire 2 3 T [1:0] $end
$var wire 2 4 P2 [1:0] $end
$var wire 2 5 P [1:0] $end
$var wire 1 $ B2 $end
$var wire 2 6 B [1:0] $end
$var wire 1 % Ac2 $end
$var wire 2 7 Ac [1:0] $end
$scope module I $end
$var wire 2 8 A [1:0] $end
$var wire 1 - PB1 $end
$var wire 1 . PB2 $end
$var wire 1 / PB3 $end
$var wire 1 0 Y $end
$var wire 1 * clk $end
$var wire 1 + reset $end
$var wire 2 9 Ta [1:0] $end
$var wire 2 : T [1:0] $end
$var wire 2 ; P [1:0] $end
$var wire 5 < EF [4:0] $end
$var wire 5 = E [4:0] $end
$var wire 2 > B [1:0] $end
$var wire 2 ? Ac [1:0] $end
$scope module S1 $end
$var wire 5 @ D [4:0] $end
$var wire 1 + clk $end
$var wire 1 * reset $end
$var reg 5 A S [4:0] $end
$upscope $end
$upscope $end
$scope module J1 $end
$var wire 1 B Out $end
$var wire 1 ' PB1 $end
$var wire 1 C Y1 $end
$var wire 1 * clk $end
$var wire 1 - out $end
$var wire 1 + reset $end
$var wire 1 D Y2 $end
$scope module E1 $end
$var wire 1 C D $end
$var wire 1 + clk $end
$var wire 1 * reset $end
$var reg 1 D S $end
$upscope $end
$upscope $end
$scope module J2 $end
$var wire 1 E Out $end
$var wire 1 ( PB2 $end
$var wire 1 F Y1 $end
$var wire 1 * clk $end
$var wire 1 . out $end
$var wire 1 + reset $end
$var wire 1 G Y2 $end
$scope module E1 $end
$var wire 1 F D $end
$var wire 1 + clk $end
$var wire 1 * reset $end
$var reg 1 G S $end
$upscope $end
$upscope $end
$scope module J3 $end
$var wire 1 H Out $end
$var wire 1 ) PB3 $end
$var wire 1 I Y1 $end
$var wire 1 * clk $end
$var wire 1 / out $end
$var wire 1 + reset $end
$var wire 1 J Y2 $end
$scope module E1 $end
$var wire 1 I D $end
$var wire 1 + clk $end
$var wire 1 * reset $end
$var reg 1 J S $end
$upscope $end
$upscope $end
$scope module W $end
$var wire 2 K T [1:0] $end
$var wire 1 " T2 $end
$var wire 1 0 Y $end
$var wire 1 * clk $end
$var wire 1 + reset $end
$var wire 2 L EF [1:0] $end
$var wire 2 M E [1:0] $end
$scope module R1 $end
$var wire 2 N D [1:0] $end
$var wire 1 + clk $end
$var wire 1 * reset $end
$var reg 2 O S [1:0] $end
$upscope $end
$upscope $end
$scope module W1 $end
$var wire 2 P Ta [1:0] $end
$var wire 1 0 Y $end
$var wire 1 * clk $end
$var wire 1 + reset $end
$var wire 2 Q Ta2 [1:0] $end
$var wire 2 R EF [1:0] $end
$var wire 2 S E [1:0] $end
$scope module R2 $end
$var wire 2 T D [1:0] $end
$var wire 1 + clk $end
$var wire 1 * reset $end
$var reg 2 U S [1:0] $end
$upscope $end
$upscope $end
$scope module W2 $end
$var wire 2 V P [1:0] $end
$var wire 1 0 Y $end
$var wire 1 * clk $end
$var wire 1 + reset $end
$var wire 2 W P2 [1:0] $end
$var wire 2 X EF [1:0] $end
$var wire 2 Y E [1:0] $end
$scope module R3 $end
$var wire 2 Z D [1:0] $end
$var wire 1 + clk $end
$var wire 1 * reset $end
$var reg 2 [ S [1:0] $end
$upscope $end
$upscope $end
$scope module W3 $end
$var wire 2 \ Ac [1:0] $end
$var wire 1 % Ac2 $end
$var wire 1 0 Y $end
$var wire 1 * clk $end
$var wire 1 + reset $end
$var wire 2 ] EF [1:0] $end
$var wire 2 ^ E [1:0] $end
$scope module R4 $end
$var wire 2 _ D [1:0] $end
$var wire 1 + clk $end
$var wire 1 * reset $end
$var reg 2 ` S [1:0] $end
$upscope $end
$upscope $end
$scope module W4 $end
$var wire 2 a B [1:0] $end
$var wire 1 $ B2 $end
$var wire 1 0 Y $end
$var wire 1 * clk $end
$var wire 1 + reset $end
$var wire 2 b EF [1:0] $end
$var wire 2 c E [1:0] $end
$scope module R5 $end
$var wire 2 d D [1:0] $end
$var wire 1 + clk $end
$var wire 1 * reset $end
$var reg 2 e S [1:0] $end
$upscope $end
$upscope $end
$upscope $end
$upscope $end
$enddefinitions $end
#0
$dumpvars
b0 e
b0 d
b0 c
b0 b
b0 a
b0 `
b0 _
b0 ^
b0 ]
b0 \
b0 [
b0 Z
b0 Y
b0 X
b1 W
b0 V
b0 U
b0 T
b0 S
b0 R
b1 Q
b0 P
b0 O
b0 N
b0 M
b0 L
b0 K
0J
xI
xH
0G
xF
xE
0D
xC
xB
b0 A
b0x @
b0 ?
b0 >
b0 =
b0x <
b0 ;
b0 :
b0 9
bx 8
b0 7
b0 6
b0 5
b1 4
b0 3
b0 2
b1 1
00
z/
z.
z-
bx ,
x+
1*
x)
x(
x'
bx &
1%
1$
b1 #
1"
b1 !
$end
#4
1+
#5
0*
#6
0+
#10
0H
0E
1B
b0 &
b0 ,
b0 8
0I
0)
0F
0(
1C
1'
1*
#15
0*
#18
0B
b1 &
b1 ,
b1 8
0C
0'
#20
1*
#25
0*
#26
1B
b0 &
b0 ,
b0 8
1C
1'
#30
1*
#34
1E
0B
1F
1(
0C
0'
#35
0*
#36
b0xx <
b0xx @
0E
b0x =
b0x A
1G
1+
#38
0+
#40
b0x <
b0x @
1E
0G
b0 =
b0 A
1*
#42
0E
1B
0F
0(
1C
1'
#45
0*
#46
1E
0B
1F
1(
0C
0'
#50
0E
b10 &
b10 ,
b10 8
0F
0(
1*
#55
0*
#58
1E
b0 &
b0 ,
b0 8
1F
1(
#60
1*
#65
0*
#68
b0xx <
b0xx @
0E
b0x =
b0x A
1G
1+
#70
b0x <
b0x @
1E
0G
b0 =
b0 A
0+
1*
#74
0E
1B
0F
0(
1C
1'
#75
0*
#78
1E
0B
1F
1(
0C
0'
#80
1*
#82
0E
b11 &
b11 ,
b11 8
0F
0(
#85
0*
#90
1E
b0 &
b0 ,
b0 8
1F
1(
1*
#94
0E
1B
0F
0(
1C
1'
#95
0*
#98
1E
0B
1F
1(
0C
0'
#100
1+
1*
#102
0+
#105
0*
#106
0E
1B
0F
0(
1C
1'
#110
1*
#114
0B
b1 &
b1 ,
b1 8
0C
0'
#115
0*
#118
b10 &
b10 ,
b10 8
#120
1*
#122
1B
b0 &
b0 ,
b0 8
1C
1'
#125
0*
#126
1E
0B
1F
1(
0C
0'
#130
1*
#132
1+
#134
0+
#135
0*
#138
0E
1B
0F
0(
1C
1'
#140
1*
#145
0*
#146
0B
b11 &
b11 ,
b11 8
0C
0'
#150
b10 &
b10 ,
b10 8
1*
#154
1E
b0 &
b0 ,
b0 8
1F
1(
#155
0*
#158
0E
1B
0F
0(
1C
1'
#160
1*
#162
1E
0B
1F
1(
0C
0'
#164
1+
#165
0*
#166
0+
#170
0E
1B
0F
0(
1C
1'
1*
#174
1E
0B
1F
1(
0C
0'
#175
0*
#178
0E
b1 &
b1 ,
b1 8
0F
0(
#180
1*
#182
1H
b0 &
b0 ,
b0 8
1I
1)
#185
0*
#186
0H
0I
0)
#190
1*
#195
0*
#196
b0xx <
b0xx @
b0x =
b0x A
1+
#198
0+
#200
b0x <
b0x @
b0 =
b0 A
1*
#202
1B
1C
1'
#205
0*
#206
1E
0B
1F
1(
0C
0'
#210
0E
b1 &
b1 ,
b1 8
0F
0(
1*
#214
b10 &
b10 ,
b10 8
#215
0*
#218
1H
b0 &
b0 ,
b0 8
1I
1)
#220
1*
#222
0H
0I
0)
